cursofiap/__init__.py
cursofiap/core.py
cursofiap_rodrigojager-1.0.0.dist-info/METADATA
cursofiap_rodrigojager-1.0.0.dist-info/WHEEL
cursofiap_rodrigojager-1.0.0.dist-info/top_level.txt
cursofiap_rodrigojager-1.0.0.dist-info/RECORD
