Metadata-Version: 2.4
Name: cursofiap-rodrigojager
Version: 1.0.0
Summary: Cursofiap
Home-page: https://github.com/rodrigojager/cursofiap
Author: Rodrigo Jäger
Author-email: rodrigojager@gmail.com
License: MIT
Dynamic: author
Dynamic: author-email
Dynamic: description
Dynamic: description-content-type
Dynamic: home-page
Dynamic: license
Dynamic: summary
